setup.py
y_w/__init__.py
y_w.egg-info/PKG-INFO
y_w.egg-info/SOURCES.txt
y_w.egg-info/dependency_links.txt
y_w.egg-info/not-zip-safe
y_w.egg-info/top_level.txt