Metadata-Version: 1.0
Name: y-w
Version: 0.1.1
Summary: YW stats package
Home-page: http://github.com/y_w
Author: Yue Weng
Author-email: wengyue31@hotmail.com
License: SJSU
Platform: UNKNOWN
